weaveio/__init__.py
weaveio/__version__.py
weaveio/command_line.py
weaveio/config_tables.py
weaveio/context.py
weaveio/data.py
weaveio/file.py
weaveio/graph.py
weaveio/helper.py
weaveio/hierarchy.py
weaveio/path_finding.py
weaveio/path_finding_old.py
weaveio/schema.py
weaveio/utilities.py
weaveio/basequery/__init__.py
weaveio/basequery/actions.py
weaveio/basequery/common.py
weaveio/basequery/dissociated.py
weaveio/basequery/factor.py
weaveio/basequery/handler.py
weaveio/basequery/hierarchy.py
weaveio/basequery/parse_tree.py
weaveio/basequery/tree.py
weaveio/basequery/tests/__init__.py
weaveio/basequery/tests/conftest.py
weaveio/basequery/tests/test_factor.py
weaveio/basequery/tests/test_hierarchy.py
weaveio/basequery/tests/test_query_execution.py
weaveio/basequery/tests/test_query_writing.py
weaveio/basequery/tests/example_structures/__init__.py
weaveio/basequery/tests/example_structures/one2one.py
weaveio/opr3/__init__.py
weaveio/opr3/expected_line_indices.csv
weaveio/opr3/expected_lines.csv
weaveio/opr3/hierarchy.py
weaveio/opr3/l1.py
weaveio/opr3/l1files.py
weaveio/opr3/l2.py
weaveio/opr3/l2files.py
weaveio/readquery/__init__.py
weaveio/readquery/aggregations.py
weaveio/readquery/align.py
weaveio/readquery/base.py
weaveio/readquery/digraph.py
weaveio/readquery/exceptions.py
weaveio/readquery/functions.py
weaveio/readquery/helpers.py
weaveio/readquery/objects.py
weaveio/readquery/parser.py
weaveio/readquery/results.py
weaveio/readquery/split.py
weaveio/readquery/statements.py
weaveio/readquery/uploads.py
weaveio/readquery/utilities.py
weaveio/readquery/wrappers.py
weaveio/tests/__init__.py
weaveio/tests/conftest.py
weaveio/tests/my_table.ascii
weaveio/tests/test_align.py
weaveio/tests/test_complex_cases.py
weaveio/tests/test_examples.py
weaveio/tests/test_find_hierarchies.py
weaveio/tests/test_splits.py
weaveio/tests/test_utilities.py
weaveio/writequery/__init__.py
weaveio/writequery/actions.py
weaveio/writequery/base.py
weaveio/writequery/merging.py
weaveio-2023.0.17.dist-info/LICENSE
weaveio-2023.0.17.dist-info/METADATA
weaveio-2023.0.17.dist-info/WHEEL
weaveio-2023.0.17.dist-info/entry_points.txt
weaveio-2023.0.17.dist-info/top_level.txt
weaveio-2023.0.17.dist-info/RECORD
