Metadata-Version: 2.1
Name: weaveio
Version: 2023.0.17
Summary: WEAVE-IO query interface for accessing WEAVE data
Home-page: https://github.com/WEAVE-LOFAR/weave-io
Author: philastrophist
Author-email: shaun.c.read@gmail.com
License: MIT
Platform: UNKNOWN
Classifier: License :: OSI Approved :: MIT License
Classifier: Programming Language :: Python
Classifier: Programming Language :: Python :: 3
Classifier: Programming Language :: Python :: 3.7
Classifier: Programming Language :: Python :: Implementation :: CPython
Classifier: Programming Language :: Python :: Implementation :: PyPy
Requires-Dist: py2neo (==2021.1.5)
Requires-Dist: xxhash (==2.0.0)
Requires-Dist: astropy (==4.0.1.post1)
Requires-Dist: networkx (==2.6.3)
Requires-Dist: numpy (==1.18.1)
Requires-Dist: pandas (==1.0.3)
Requires-Dist: pytest (==5.4.1)
Requires-Dist: tqdm
Requires-Dist: colored
Requires-Dist: pkg-info
Requires-Dist: semver
Requires-Dist: textdistance
Requires-Dist: inflect (==5.3.0)
Requires-Dist: graphviz
Requires-Dist: matplotlib
Requires-Dist: jupyter
Requires-Dist: notebook
Requires-Dist: ipython
Requires-Dist: scipy
Requires-Dist: timeout-decorator
